{
  "Appelt Hall": {
    "lat": 30.6142844,
    "lng": -96.3353588
  },
  "Aston Hall": {
    "lat": 30.6145941,
    "lng": -96.3361978
  },
  "Clements Hall": {
    "lat": 30.6143772,
    "lng": -96.34547769999999
  },
  "Dunn Hall": {
    "lat": 30.6152296,
    "lng": -96.3365981
  },
  "Eppright Hall": {
    "lat": 30.6143362,
    "lng": -96.3345103
  },
  "Fowler Hall": {
    "lat": 30.6148025,
    "lng": -96.3455697
  },
  "Hart Hall": {
    "lat": 30.6142793,
    "lng": -96.3406231
  },
  "Haas Hall": {
    "lat": 30.6161338,
    "lng": -96.3442963
  },
  "Hobby Hall": {
    "lat": 30.6177758,
    "lng": -96.3439176
  },
  "Hughes Hall": {
    "lat": 30.6152849,
    "lng": -96.34498939999999
  },
  "Hullabaloo Hall": {
    "lat": 30.61695940399832,
    "lng": -96.34624744540113
  },
  "Krueger Hall": {
    "lat": 30.6161027,
    "lng": -96.3356943
  },
  "Lechner Hall": {
    "lat": 30.6161658,
    "lng": -96.3438497
  },
  "McFadden Hall": {
    "lat": 30.6155917,
    "lng": -96.344233
  },
  "Moses Hall": {
    "lat": 30.6157825,
    "lng": -96.3454398
  },
  "Mosher Hall": {
    "lat": 30.6156312,
    "lng": -96.3349337
  },
  "Neeley Hall": {
    "lat": 30.6180014,
    "lng": -96.3444121
  },
  "Rudder Hall": {
    "lat": 30.6150134,
    "lng": -96.3341751
  },
  "Schuhmacher Hall": {
    "lat": 30.6171626,
    "lng": -96.34545899999999
  },
  "Underwood Hall": {
    "lat": 30.6140917,
    "lng": -96.3356404
  },
  "Walton Hall": {
    "lat": 30.6168292,
    "lng": -96.34516269999999
  },
  "Wells Hall": {
    "lat": 30.6149339,
    "lng": -96.33497299999999
  },
  "Keathley Hall": {
    "lat": 30.6152045,
    "lng": -96.3455903
  }
}